LICENSE
setup.py
yolov7/__init__.py
yolov7/config.py
yolov7/version.py
yolov7/modeling/__init__.py
yolov7/modeling/backbone/__init__.py
yolov7/modeling/backbone/anchordetr_backbone.py
yolov7/modeling/backbone/cfg.py
yolov7/modeling/backbone/convnext.py
yolov7/modeling/backbone/cspdarknet.py
yolov7/modeling/backbone/cspresnet.py
yolov7/modeling/backbone/dabdetr_backbone.py
yolov7/modeling/backbone/darknet.py
yolov7/modeling/backbone/darknetx.py
yolov7/modeling/backbone/detr_backbone.py
yolov7/modeling/backbone/dla.py
yolov7/modeling/backbone/dlafpn.py
yolov7/modeling/backbone/efficientnet.py
yolov7/modeling/backbone/efficientrep.py
yolov7/modeling/backbone/fbnet_v2.py
yolov7/modeling/backbone/fbnet_v3.py
yolov7/modeling/backbone/mobilevit.py
yolov7/modeling/backbone/pvt_v2.py
yolov7/modeling/backbone/regnet.py
yolov7/modeling/backbone/resnetvd.py
yolov7/modeling/backbone/smcadetr_backbone.py
yolov7/modeling/backbone/swin_transformer.py
yolov7/modeling/backbone/volo.py
yolov7/modeling/backbone/yolov5_backbone.py
yolov7/modeling/backbone/layers/__init__.py
yolov7/modeling/backbone/layers/activations.py
yolov7/modeling/backbone/layers/row_column_decoupled_attention.py
yolov7/modeling/backbone/layers/smca_attention.py
yolov7/modeling/backbone/layers/utils.py
yolov7/modeling/backbone/layers/wrappers.py
yolov7/modeling/backbone/res2nets/__init__.py
yolov7/modeling/backbone/res2nets/res2net.py
yolov7/modeling/backbone/res2nets/res2net_v1b.py
yolov7/modeling/backbone/res2nets/res2next.py
yolov7/modeling/backbone/res2nets/wrapper.py
yolov7/modeling/head/__init__.py
yolov7/modeling/head/box_regression.py
yolov7/modeling/head/decoder.py
yolov7/modeling/head/effidehead.py
yolov7/modeling/head/encoder.py
yolov7/modeling/head/sem_seg_head.py
yolov7/modeling/head/solov2_head.py
yolov7/modeling/head/uniform_matcher.py
yolov7/modeling/head/yolov6_head.py
yolov7/modeling/head/yolox_head.py
yolov7/modeling/head/yolox_kpts_head.py
yolov7/modeling/meta_arch/__init__.py
yolov7_d2.egg-info/PKG-INFO
yolov7_d2.egg-info/SOURCES.txt
yolov7_d2.egg-info/dependency_links.txt
yolov7_d2.egg-info/not-zip-safe
yolov7_d2.egg-info/top_level.txt